Workbook

Sheet Reference Catalog
A1: Entity | B1: Business Definition | C1: Business Purpose | D1: Code / Key | E1: Value / Description | F1: Parent Reference | G1: Hierarchy | H1: Status | I1: Source | J1: Owner | K1: Related Process | L1: Related Transactions | M1: Notes
A2: Campaign Type | B2: مرجع انواع کمپین‌های بازاریابی؛ هر نوع با شناسه و نام نوع مشخص می‌شود. | C2: طبقه‌بندی یکپارچه کمپین‌ها و فراهم‌کردن امکان انتخاب نوع کمپین و تحلیل آن بر اساس نوع. | D2: Campaign_Type_ID | E2: Type_Name؛ Description | F2: مشخص نشده؛ Open / To Be Confirmed | G2: تک‌سطحی در اطلاعات موجود؛ وجود زیرنوع تأیید نشده است. | H2: Open / To Be Confirmed | I2: Marketing Campaign؛ Campaign Type (مرحله 05) | J2: Marketing | K2: تعریف و مدیریت کمپین بازاریابی | L2: Marketing Campaign | M2: Campaign_Type_ID و Type_Name وضعیت Confirmed دارند. Description وضعیت Open / To Be Confirmed دارد؛ حداکثر طول و پشتیبانی از متن چندزبانه نیازمند تصمیم است. فهرست مقادیر مجاز و وضعیت مرجع نهایی مشخص نشده‌اند. | [Merge Log] DC-24, DC-30; OD-25
A3: Campaign Channel | B3: فهرست مرجع کانال‌ها یا رسانه‌های مورد استفاده برای اجرای کمپین‌های بازاریابی. | C3: استانداردسازی کانال‌های بازاریابی و پشتیبانی از انتخاب کانال در کمپین‌ها و تحلیل عملکرد بر اساس کانال. | D3: Channel_ID | E3: Channel_Name؛ Channel_Type؛ Channel_Description | F3: مشخص نشده؛ Open / To Be Confirmed | G3: تک‌سطحی در اطلاعات موجود؛ ساختار سلسله‌مراتبی تأیید نشده است. | H3: Open / To Be Confirmed | I3: Campaign & Advertising؛ Campaign Channel (مرحله 05) | J3: Product & Marketing | K3: مدیریت کانال و اجرای کمپین‌های بازاریابی | L3: Marketing Campaign (از طریق Campaign_ID / Channel_ID؛ نگاشت نهایی نیازمند تأیید) | M3: Channel_Description و Channel_Status در مرحله 05 Confirmed هستند؛ برای وضعیت، مقادیر نمونه Active / Inactive ذکر شده است. Channel_ID، Channel_Name و Channel_Type دارای موارد باز و تعارض میان منابع هستند: Channel_ID در برابر ChannelID، تفاوت نوع داده و قالب. فهرست نهایی مقادیر Channel_Type و سیستم منبع دقیق تأیید نشده است. Campaign_ID در همین Entity با Classification=Transactional آمده و در این کاتالوگ به‌عنوان کلید مرجع تلقی نشده است. | [Merge Log] DC-24, DC-25; OD-16, OD-25
A4: Campaign Audience | B4: فهرست مرجع گروه‌های مخاطب هدف که برای هدف‌گذاری کمپین‌های بازاریابی به کار می‌روند. | C4: استانداردسازی گروه‌های مخاطب و امکان انتخاب و تحلیل کمپین‌ها بر اساس مخاطب هدف. | D4: Audience_ID | E4: Audience_Name؛ Audience_Type؛ Audience_Description | F4: مشخص نشده؛ Open / To Be Confirmed | G4: تک‌سطحی در اطلاعات موجود؛ سلسله‌مراتب مخاطبان تأیید نشده است. | H4: Open / To Be Confirmed | I4: Campaign & Advertising؛ Campaign Audience (مرحله 05) | J4: Product & Marketing | K4: تعریف مخاطب و هدف‌گذاری کمپین | L4: Marketing Campaign (از طریق Campaign_ID؛ ارتباط دقیق نیازمند تأیید) | M4: Audience_Description و Audience_Status در مرحله 05 Confirmed هستند؛ مقادیر نمونه وضعیت Active / Inactive است. Audience_ID و Audience_Name دارای تعارض نام‌گذاری و طبقه‌بندی بین F6 و F7 هستند؛ انتخاب موقت Reference در مرحله 05 ثبت شده است. تصمیم باز: مخاطب مرجع قابل استفاده مجدد است یا مختص کمپین؟ نوع داده، قالب، یکتایی نام و سیستم منبع دقیق نیز نیازمند تأییدند. Demographics در همین Entity با Classification=Master است و در این کاتالوگ وارد نشده؛ Campaign_ID با Classification=Transactional است. | [Merge Log] DC-22, DC-24; OD-12, OD-25
A5: Product Category | B5: دسته اصلی محصولات که کالاها بر اساس آن گروه‌بندی می‌شوند | C5: گروه‌بندی کلی محصولات برای گزارش‌گیری، تحلیل فروش و مدیریت سبد محصول | D5: Open / To Be Confirmed (Product_Category_ID یا CategoryID؟) | E5: نمونه پیشنهادی (نیازمند تأیید): نوشیدنی، لبنیات، خشکبار | F5: Open / To Be Confirmed | G5: Open / To Be Confirmed (بسته به مدل انتخابی: Entity جدا یا درخت خودارجاع) | H5: Open / To Be Confirmed | I5: مرجع دسته‌بندی محصول (کاتالوگ محصول) | J5: Product & Marketing (مدیریت محصول) | K5: مدیریت محصولات | L5: تراکنش مستقیم ثبت نشده؛ از طریق Product (Master) و به‌صورت غیرمستقیم در Sales Order Item (تیم ۱) | M5: این Entity با سه ساختار و نام‌گذاری متفاوت مطرح شده (Product Category / CategoryID / ساختار درختی)؛ ساختار نهایی و نام کلید در مرحله Merge تعیین می‌شود | [Merge Log] DC-25, DC-27; OD-21, OD-22
A6: Product Subcategory | B6: زیرمجموعه دقیق‌تر یک دسته محصول | C6: تحلیل ریزتر فروش و موجودی در سطحی پایین‌تر از دسته اصلی | D6: Subcategory_ID (نام‌گذاری با SubcategoryID هم دیده شده؛ Open / To Be Confirmed) | E6: نمونه پیشنهادی (نیازمند تأیید): آبمیوه، نوشابه، دوغ | F6: Open / To Be Confirmed (Product Category، فقط اگر مدل «Entity جدا» انتخاب شود) | G6: Open / To Be Confirmed (در مدل درختی، زیردسته همان Product Category با سطح بالاتر است) | H6: Open / To Be Confirmed | I6: مرجع دسته‌بندی محصول (کاتالوگ محصول) | J6: Product & Marketing (مدیریت محصول) | K6: مدیریت محصولات | L6: تراکنش مستقیم ثبت نشده؛ از طریق Product (Master) و به‌صورت غیرمستقیم در Sales Order Item (تیم ۱) | M6: برای سلسله‌مراتب دسته‌بندی دو مدل مطرح است (Entity جدا یا درخت خودارجاع)؛ اگر مدل درختی انتخاب شود این Entity زائد می‌شود، پس تصمیم نهایی در Merge گرفته می‌شود و فعلاً حدس زده نشد | [Merge Log] DC-27; OD-21
A7: Package | B7: نوع بسته‌بندی محصول در سطح واحد قابل فروش (بطری، کارتن، پاکت) | C7: مشخص کردن شکل عرضه محصول برای فروش، انبارداری و توزیع | D7: Package_ID / Package_Code | E7: بطری، کارتن، پاکت | F7: — | G7: تک‌سطحی (زیرمجموعه ندارد) | H7: Defined | I7: سیستم مدیریت محصولات | J7: Product & Marketing | K7: مدیریت محصولات | L7: تراکنش مستقیم ثبت نشده؛ استفاده از طریق SKU (Master) و در تراکنش‌های فروش تیم ۱ به‌صورت غیرمستقیم؛ در Merge با تیم ۱ تأیید شود | M7: مشخص نیست وزن بسته‌بندی جزو مشخصات Package است یا Product؛ نیازمند تصمیم تیم مدیریت محصول | [Merge Log] DC-26; OD-23
A8: Unit Of Measure | B8: واحد اندازه‌گیری استاندارد محصول (کیلوگرم، لیتر، عدد) | C8: یکسان‌سازی واحد گزارش موجودی، فروش و قیمت‌گذاری | D8: UOM_ID / UOM_Code | E8: کیلوگرم (KG)، لیتر (LT)، عدد (PCS) | F8: — | G8: تک‌سطحی (زیرمجموعه ندارد) | H8: Defined | I8: سیستم مدیریت محصولات | J8: Product & Marketing | K8: مدیریت محصولات | L8: تراکنش مستقیم ثبت نشده؛ استفاده از طریق SKU و Product (Base_UOM_ID) که Master هستند؛ در Merge با تیم ۱ تأیید شود | M8: املای نام (Unit Of Measure / Unit of Measure) در مرحله Merge یکدست شود؛ واحد پایه محصول هنوز مشخص نیست | [Merge Log] DC-26; OD-23
A9: Product Price | B9: قیمت واحد محصول همراه با بازه اعتبار (تاریخ اجرای قیمت) | C9: منبع اصلی قیمت محصول؛ هر تغییر قیمت با تاریخ اجرا در آن ثبت می‌شود | D9: Open / To Be Confirmed | E9: مقدار قیمت واحد در یک بازه زمانی مشخص | F9: — | G9: تک‌سطحی | H9: Open / To Be Confirmed | I9: سیستم قیمت‌گذاری / ERP | J9: Product & Marketing (تصمیم‌گیر: مدیریت فروش / قیمت‌گذاری) | K9: مدیریت محصولات، قیمت‌گذاری | L9: Sales Order Item، Contract Item، Invoice Item (تیم ۱، Unit_Price)؛ Order_Line_Item (Unit_Price_Snapshot) | M9: پیشنهاد: Product Price منبع اصلی قیمت باشد و Base_Price روی Product مقدار جاری یا حذف شود؛ تصمیم نهایی هنوز گرفته نشده. قیمت ثبت‌شده در سفارش یک Snapshot مستقل است | [Merge Log] DC-28, DC-29; OD-24

Sheet Transactional Catalog
A1: Entity | B1: Business Definition | C1: Related Process | D1: Transaction Type | E1: Business Event | F1: Business Grain | G1: Business Date | H1: Status | I1: Source | J1: Owner | K1: Related Master | L1: Related Reference | M1: Related Transaction | N1: Notes
A2: Market Research | B2: فرآیند تحقیق بازار برای جمع‌آوری و بررسی اطلاعات موردنیاز کسب‌وکار. | C2: Market Research | D2: Research Activity | E2: ثبت شروع، اجرای و پایان یک فرآیند تحقیق بازار. | F2: هر رکورد = یک فرآیند/پروژه تحقیق بازار. | G2: Start_Date / End_Date | H2: Research_Status | I2: Market Research System | J2: Marketing | K2: — | L2: — | M2: Market Survey | N2: Business Purpose از تعریف Attributeها استنباط شده است. Conflict: خود Entity در 4.1 Transactional است، اما Attributeهای آن در Stage 05 عمدتاً Planning طبقه‌بندی شده‌اند؛ تصمیم نهایی در Open Decisions. | [Merge Log] DC-01..DC-03, DC-08, DC-09, DC-14؛ OD-01..OD-04
A3: Market Survey | B3: فعالیت/ابزار Survey برای جمع‌آوری داده در یک تحقیق بازار. | C3: Market Research | D3: Survey Activity | E3: ثبت اجرای Survey برای جمع‌آوری داده‌های بازار. | F3: هر رکورد = یک Survey/فعالیت نظرسنجی در چارچوب یک تحقیق بازار. | G3: Survey_Date | H3: Survey_Status | I3: Market Survey System | J3: Marketing | K3: — | L3: Market Segment | M3: Market Research | N3: Market Segment در Attribute Segment_ID به‌عنوان Related Entity آمده است؛ وجود آن در Final Entity Catalog باید با نسخه نهایی کنترل شود. | [Merge Log] DC-01, DC-04..DC-06, DC-08؛ OD-03, OD-05
A4: Market Price | B4: رکورد قیمت مشاهده‌شده یک محصول در بازار. | C4: Market Price Monitoring | D4: Price Observation | E4: ثبت مشاهده و ثبت قیمت محصول/قیمت مرتبط با رقیب در بازار. | F4: هر رکورد = یک مشاهده قیمت برای یک Product در یک Market و یک تاریخ؛ Competitor در صورت وجود. | G4: Price_Date | H4: — | I4: Market Price Monitoring System | J4: Marketing / Sales | K4: Product; Competitor | L4: — | M4: — | N4: Status در Attributeهای Stage 05 تعریف نشده است؛ نباید Status جدید حدس زده شود. Price_Value صراحتاً قیمت مشاهده‌شده بازار است، نه قیمت فروش داخلی. | [Merge Log] DC-01, DC-05, DC-07, DC-08, DC-29؛ OD-04, OD-08, OD-26
A5: Brand Activity | B5: هر فعالیت اجرایی مرتبط با مدیریت یا توسعه برند. | C5: Branding | D5: Brand Activity | E5: ثبت ایجاد/شروع/اجرای یک فعالیت برند. | F5: هر رکورد = یک فعالیت مشخص مرتبط با یک Brand. | G5: Activity_Start_Date / Activity_End_Date | H5: Activity_Status | I5: فرایند: برندینگ؛ سیستم: To Be Confirmed | J5: To Be Confirmed | K5: Brand | L5: Campaign Channel | M5: — | N5: Owner در Stage 05 مشخص نشده است. رابطه مستقیم با Brand Campaign در Dictionary تعریف نشده؛ فقط Brand مشترک است، بنابراین به‌عنوان Transaction Relationship قطعی فرض نشده. | [Merge Log] DC-13, DC-30؛ OD-13, OD-15
A6: Brand Campaign | B6: کمپینی با هدف توسعه آگاهی، هویت یا جایگاه برند. | C6: Branding | D6: Brand Campaign | E6: ثبت ایجاد و اجرای یک کمپین برند. | F6: هر رکورد = یک کمپین مشخص برای یک Brand. | G6: Campaign_Start_Date / Campaign_End_Date | H6: Campaign_Status | I6: فرایند: برندینگ؛ سیستم: To Be Confirmed | J6: To Be Confirmed | K6: Brand | L6: Campaign Type; Campaign Channel; Campaign Audience | M6: Campaign Cost | N6: Campaign Budget از نوع Planning و Campaign Result از نوع Analytical/Performance هستند و در Related Transaction قرار نمی‌گیرند. Campaign Cost با Attribute جداگانه در Brand Campaign و Entity Campaign Cost دارای Overlap است؛ نگاشت نهایی باز است. | [Merge Log] DC-10..DC-13, DC-24؛ OD-07, OD-13, OD-16
A7: Marketing Campaign | B7: کمپین اجرایی بازاریابی که برای یک هدف مشخص برنامه‌ریزی و اجرا می‌شود. | C7: Marketing Campaign | D7: Marketing Campaign | E7: ثبت ایجاد، شروع، اجرا، توقف یا تکمیل یک کمپین بازاریابی. | F7: هر رکورد = یک کمپین اجرایی بازاریابی در یک دوره مشخص. | G7: Start_Date / End_Date | H7: Campaign_Status | I7: Marketing Campaign; فرایند: کمپین بازاریابی؛ سیستم: To Be Confirmed | J7: Marketing | K7: — | L7: Campaign Type; Campaign Channel; Campaign Audience | M7: Campaign Cost; Promotion | N7: Start_Date/End_Date در Stage 05 Planning و Campaign_Status در Stage 05 Reference طبقه‌بندی شده‌اند؛ در 4.1 خود Entity Transactional است. Conflict باید حفظ و در Merge/Open Decisions بررسی شود. | [Merge Log] DC-12, DC-14..DC-16, DC-24؛ OD-10, OD-11
A8: Campaign Cost | B8: رکورد هزینه واقعی انجام‌شده برای یک کمپین. | C8: Marketing Campaign | D8: Actual Cost | E8: ثبت وقوع و ثبت یک هزینه واقعی کمپین. | F8: هر رکورد = یک ردیف هزینه واقعی برای یک Campaign در یک Cost_Date. | G8: Cost_Date | H8: — | I8: Campaign Cost; فرایند: کمپین بازاریابی؛ سیستم: To Be Confirmed | J8: Marketing / Finance | K8: — | L8: — | M8: Marketing Campaign | N8: Status در Attributeهای Stage 05 تعریف نشده است. Campaign_ID صراحتاً به Marketing Campaign مرتبط است. پوشش هزینه Brand Campaign در Stage 05 باز و نیازمند تصمیم است؛ دوباره‌شماری نباید فرض شود. | [Merge Log] DC-10, DC-11, DC-15, DC-30؛ OD-07, OD-08, OD-15
A9: Promotion | B9: پیشنهاد تجاری/بازاریابی شامل نوع Promotion، شرایط و بازه اعتبار آن. | C9: Marketing / Campaign & Advertising | D9: Promotion Definition / Activation | E9: تعریف، فعال‌سازی یا تغییر وضعیت یک Promotion. | F9: هر رکورد = یک Promotion با مشخصات کسب‌وکاری و بازه اعتبار. | G9: Valid_From / Valid_To | H9: Promotion_Status | I9: Marketing / Sales | J9: Team 1 | K9: — | L9: — | M9: Marketing Campaign; Sales Order | N9: Shared Entity است؛ مالکیت اصلی با Team 1 است و Team 2 فقط خاستگاه/منطق بازاریابی Promotion را مستند می‌کند. جزئیات اعمال Promotion در Sales Order در محدوده Team 1 است. | [Merge Log] DC-33؛ SD-01؛ OD-09, OD-11, OD-18

Sheet Reference-Transaction Mapping
A1: Mapping ID | B1: Transaction | C1: Reference | D1: Business Use | E1: Mandatory? | F1: Notes
A2: MAP-001 | B2: Brand Activity | C2: Campaign Channel | D2: مشخص‌کردن کانال/رسانه‌ای که یک فعالیت برند از طریق آن اجرا می‌شود و امکان تحلیل فعالیت‌های برند بر اساس کانال. | E2: To Be Confirmed | F2: منبع: Related Reference ردیف Brand Activity در کاتالوگ تراکنشی. متن Business Use از Business Purpose مرجع Campaign Channel استخراج شده و در Stage 05 صراحتاً برای Brand Activity ذکر نشده. در کاتالوگ Reference (Task 4.6.2) این ارتباط ثبت نشده (فقط Marketing Campaign). Mandatory نامشخص است. رابطه مستقیم Brand Activity با Brand Campaign قطعی نیست و در این Mapping وارد نشده. | [Merge] Linked: TR-009 (DC-17)؛ DC-24؛ OD-16
A3: MAP-002 | B3: Brand Campaign | C3: Campaign Type | D3: طبقه‌بندی کمپین برند بر اساس نوع کمپین و تحلیل کمپین‌ها بر اساس نوع. | E3: To Be Confirmed | F3: منبع: Related Reference ردیف Brand Campaign. در کاتالوگ Reference (Task 4.6.2) فقط Marketing Campaign به‌عنوان Related Transaction ثبت شده؛ ارتباط با Brand Campaign فقط در کاتالوگ تراکنشی آمده و باید دوطرفه تأیید شود. فهرست مقادیر مجاز Campaign Type و وضعیت مرجع نهایی (Open / To Be Confirmed) هنوز مشخص نیست. Mandatory نامشخص است. | [Merge] Linked: TR-011 (DC-17)؛ DC-24؛ OD-16
A4: MAP-003 | B4: Brand Campaign | C4: Campaign Channel | D4: مشخص‌کردن کانال‌های اجرای کمپین برند و تحلیل عملکرد بر اساس کانال. | E4: To Be Confirmed | F4: منبع: Related Reference ردیف Brand Campaign. در کاتالوگ Reference (Task 4.6.2) فقط Marketing Campaign به‌عنوان Related Transaction ثبت شده؛ ارتباط با Brand Campaign فقط در کاتالوگ تراکنشی آمده و باید دوطرفه تأیید شود. نگاشت از طریق Campaign_ID / Channel_ID در مرجع «نیازمند تأیید» ثبت شده است. Mandatory و چندگانه‌بودن (یک یا چند کانال برای هر کمپین) نامشخص است. | [Merge] Linked: TR-012 (DC-17)؛ DC-24؛ OD-16
A5: MAP-004 | B5: Brand Campaign | C5: Campaign Audience | D5: تعیین مخاطب هدف کمپین برند و تحلیل کمپین‌ها بر اساس مخاطب. | E5: To Be Confirmed | F5: منبع: Related Reference ردیف Brand Campaign. در کاتالوگ Reference (Task 4.6.2) فقط Marketing Campaign به‌عنوان Related Transaction ثبت شده؛ ارتباط با Brand Campaign فقط در کاتالوگ تراکنشی آمده و باید دوطرفه تأیید شود. تصمیم باز در مرجع: Audience قابل استفاده مجدد است یا مختص کمپین؟ Mandatory نامشخص است. | [Merge] Linked: TR-013 (DC-17)؛ DC-24؛ OD-16
A6: MAP-005 | B6: Marketing Campaign | C6: Campaign Type | D6: انتخاب و ثبت نوع کمپین بازاریابی و تحلیل کمپین‌ها بر اساس نوع. | E6: To Be Confirmed | F6: هر دو کاتالوگ (تراکنشی و Reference) این ارتباط را ثبت کرده‌اند. فهرست مقادیر مجاز و وضعیت مرجع نهایی Open / To Be Confirmed است. Mandatory نامشخص است. | [Merge] Linked: TR-015 (DC-17)؛ DC-24؛ OD-16
A7: MAP-006 | B7: Marketing Campaign | C7: Campaign Channel | D7: انتخاب کانال/رسانه اجرای کمپین بازاریابی و تحلیل عملکرد بر اساس کانال. | E7: To Be Confirmed | F7: هر دو کاتالوگ این ارتباط را ثبت کرده‌اند؛ اما در مرجع، نگاشت نهایی (Campaign_ID / Channel_ID) «نیازمند تأیید» است. در Channel_ID، Channel_Name و Channel_Type تعارض میان منابع وجود دارد. Mandatory و چندگانه‌بودن نامشخص است. | [Merge] Linked: TR-016 (DC-17)؛ DC-24؛ OD-16
A8: MAP-007 | B8: Marketing Campaign | C8: Campaign Audience | D8: هدف‌گذاری کمپین بازاریابی روی گروه مخاطب هدف و تحلیل کمپین‌ها بر اساس مخاطب. | E8: To Be Confirmed | F8: هر دو کاتالوگ این ارتباط را ثبت کرده‌اند؛ ارتباط دقیق در مرجع «نیازمند تأیید» است. تصمیم باز: Audience مرجع قابل استفاده مجدد است یا مختص کمپین. Mandatory نامشخص است. | [Merge] Linked: TR-017 (DC-17)؛ DC-24؛ OD-16

Sheet Transaction Relationships
A1: Relationship ID | B1: From Entity | C1: Relationship Type | D1: Relationship Verb | E1: To Entity | F1: To Entity Class | G1: Business Meaning | H1: Mandatory? | I1: Cardinality Review | J1: Notes
A2: TR-001 | B2: Market Research | C2: 1:N | E2: Market Survey | F2: Transactional (Team 2 catalog) | G2: یک Market Research ممکن است برای جمع‌آوری اطلاعات بازار، از یک یا چند Market Survey استفاده کند.مثلا برای تحقیق بازار ممکن است: Survey از مصرف‌کنندگان Survey از خرده‌فروشان Survey درباره میزان شناخت برندها انجام شود. | H2: To Be Confirmed | J2: To be confirmed برای اینکه مشخص کنیم آیا هر Research حتماً حداقل یک Survey دارد؟ ممکن است بعضی Researchها از داده‌های ثانویه، گزارش‌های قبلی، داده‌های فروش یا منابع دیگر استفاده کنند و اصلاً Survey نداشته باشند.
A3: TR-002 | B3: Market Research | C3: 1:N | E3: Market | F3: Unclassified - Open (OD-04) | G3: هر رکورد یا مورد از Market Research مربوط به یک Market مشخص است که قرار است مورد بررسی قرار بگیرد. تحقیق بازار در ارتباط با / درباره‌ی یک بازار مشخص انجام می‌شود. یک نکته هم وجود دارد این که هر Market Research باید به Market مورد بررسی خود مرتبط باشد، اما مشخص نیست هر Research دقیقاً یک Market دارد یا می‌تواند چند Market داشته باشد. پس ارتباط می تواند ۱ به ۱ هم باشد | H3: Yes | I3: Unclear: ثبت‌شده 1:N؛ متن N:1 یا 1:1 یا N:M؟ (OD-20) | J3: Yes به این علت که Market Research باید مشخص کند درباره کدام Market انجام شده است. | [Merge Log] DC-19; OD-04, OD-20
A4: TR-003 | B4: Market Research | C4: N:1 | E4: Market Research Type | F4: Unclassified - Open (OD-03) | G4: هر Market Research بر اساس یک Market Research Type مشخص دسته‌بندی می‌شود. مثلاً انواع تحقیق بازار در سازمان این‌ها باشند: Customer Research Competitor Research Product Research Market Size Research اگر یک Transaction از نوع: Market Research = بررسی رفتار مشتریان باشد، می‌تواند به: Market Research Type = Customer Research مرتبط شود. هر Market Research دقیقاً یک Research Type دارد، ولی یک Research Type می‌تواند برای چند Market Research استفاده شود. | H4: To Be Confirmed | J4: To be confirmed برای اینکه مشخص کنیم آیا هر Market Research حتماً باید یک Market Research Type داشته باشد؟ | [Merge Log] OD-03
A5: TR-004 | B5: Market Survey | C5: 1:N | E5: Market Segment | F5: Unclassified - Open (OD-05) | G5: یک Market Survey برای بررسی یک Market Segment مشخص انجام می‌شود. مثلاً: Market Survey: بررسی میزان رضایت مشتریان از یک محصول Market Segment: جوانان 18 تا 30 سال یعنی Survey مشخص می‌کند که داده‌ها از کدام Segment جمع‌آوری شده‌اند. هر Market Survey برای یک Segment مشخص انجام می‌شود، ولی یک Segment می‌تواند در چند Survey مورد بررسی قرار بگیرد. | H5: Yes | I5: Proposed N:1 per Business Meaning - confirm (OD-20) | J5: [Merge Log] DC-18; OD-05, OD-20
A6: TR-005 | B6: Market Survey | C6: N:M | E6: Survey Method | F6: Unclassified - Open (OD-03) | G6: یک Survey میتواند چند Method داشته باشد، مثلاً هم Online Questionnaire و هم Interview، و هر Method هم در چند Survey استفاده شود، رابطه N:M خواهد بود. | H6: To Be Confirmed | J6: باید ببینیم چند Survey می‌توانند از یک Method استفاده کنند. | [Merge Log] OD-03
A7: TR-006 | B7: Market Price | C7: N:1 | E7: Product | F7: Master (documented in Transactional Catalog) | G7: هر Market Price یک مشاهده/ثبت قیمت از یک Product مشخص است. رابطه ۱ به چند چون قیمت یک محصول می‌تواند در تاریخ‌ها، بازارها یا مشاهدات مختلف چندین بار ثبت شود. | H7: Yes
A8: TR-007 | B8: Market Price | C8: N:1 | E8: Competitor | F8: Master (documented in Transactional Catalog) | G8: یک Market Price ممکن است مشخص کند این قیمت توسط کدام Competitor یا منبع رقیب مشاهده شده است. | H8: No | J8: وجود Competitor برای ثبت Market Price اجباری نیست.
A9: TR-008 | B9: Brand Activity | C9: N:1 | E9: Brand | F9: Master (documented in Transactional Catalog) | G9: هر Brand Activity مربوط به یک Brand مشخص است؛ یعنی فعالیتی که ثبت شده، برای مدیریت یا اجرای فعالیت‌های همان برند انجام می‌شود.مثلاً Brand Activity می‌تواند فعالیتی مثل اجرای یک برنامه تبلیغاتی یا فعالیت بازاریابی مرتبط با Brand A باشد. | H9: To Be Confirmed | J9: آیا هر Brand Activity حتماً باید یک Brand داشته باشد؟
A10: TR-009 | B10: Brand Activity | C10: N:M | E10: Campaign Channel | F10: Reference (Team 2 catalog) | G10: یک Brand Activity ممکن است از یک یا چند Campaign Channel برای اجرا یا ارتباط با مخاطب استفاده کند. مثلاً: Brand Activity: معرفی محصول جدید برند X Campaign Channel: Instagram TV Website Email یعنی فعالیت برند از طریق یک کانال یا چند کانال اجرا می‌شود. | H10: To Be Confirmed | J10: آیا هر Brand Activity حتماً باید Channel داشته باشد؟ آیا یک Activity می‌تواند چند Channel داشته باشد؟ | [Merge Log] DC-17 (=MAP-001)
A11: TR-010 | B11: Brand Campaign | C11: N:1 | E11: Brand | F11: Master (documented in Transactional Catalog) | G11: هر Brand Campaign مربوط به یک Brand مشخص است و Campaign برای همان Brand اجرا می‌شود. | H11: Yes
A12: TR-011 | B12: Brand Campaign | C12: 1:N | E12: Brand Campaign Type | F12: Unclassified - Open (OD-06) | G12: هر Brand Campaign بر اساس یک Campaign Type دسته‌بندی می‌شود. Brand Campaign = New Product Launch Brand Campaign Type = Product Launch پس Brand Campaign Type مشخص می‌کند این Campaign از چه نوعی است. | H12: To Be Confirmed | I12: Proposed N:1 per Business Meaning - confirm (OD-20) | J12: آیا هر Brand Campaign حتماً باید یک Campaign Type داشته باشد؟ | [Merge Log] DC-17 (=MAP-002), DC-18, DC-20; OD-06
A13: TR-012 | B13: Brand Campaign | C13: 1:N | E13: Campaign Channel | F13: Reference (Team 2 catalog) | G13: یک Brand Campaign برای اجرا و رساندن پیام Campaign می‌تواند از یک یا چند Campaign Channel استفاده کند. مثلاً: Brand Campaign: کمپین تابستانی برند X ممکن است از این Channelها استفاده کند: Instagram TV Website Email | H13: Yes | I13: Likely N:M - confirm (OD-20) | J13: [Merge Log] DC-17 (=MAP-003), DC-19, DC-21; OD-16
A14: TR-013 | B14: Brand Campaign | C14: TBC | D14: Targets | E14: Campaign Audience | F14: Reference (Team 2 catalog) | G14: A Brand Campaign is associated with its intended audience. | H14: To Be Confirmed | I14: Cardinality TBC (OD-20) | J14: Explicitly listed under Related Master; business classification should be confirmed. | [Merge Log] DC-17 (=MAP-004), DC-22, DC-23; OD-12
A15: TR-014 | B15: Brand Campaign | C15: TBC | D15: Associated With | E15: Campaign Cost | F15: Transactional (Team 2 catalog) | G15: A Brand Campaign may have associated campaign cost information. | H15: To Be Confirmed | I15: Cardinality TBC (OD-20) | J15: Source lists Campaign Cost as Related Reference, but Campaign Cost is classified as Transactional in the same transactional catalog. Classification conflict must be resolved. | [Merge Log] DC-11, DC-23; OD-07
A16: TR-015 | B16: Marketing Campaign | C16: TBC | D16: Classified By | E16: Campaign Type | F16: Reference (Team 2 catalog) | G16: A Marketing Campaign is categorized by its campaign type. | H16: To Be Confirmed | I16: Cardinality TBC (OD-20) | J16: Explicitly listed as Related Reference in the transactional catalog. | [Merge Log] DC-17 (=MAP-005), DC-23
A17: TR-016 | B17: Marketing Campaign | C17: TBC | D17: Uses | E17: Campaign Channel | F17: Reference (Team 2 catalog) | G17: A Marketing Campaign is executed through defined campaign channels. | H17: To Be Confirmed | I17: Cardinality TBC (OD-20) | J17: Explicitly listed as Related Reference. | [Merge Log] DC-17 (=MAP-006), DC-23
A18: TR-017 | B18: Marketing Campaign | C18: TBC | D18: Targets | E18: Campaign Audience | F18: Reference (Team 2 catalog) | G18: A Marketing Campaign is associated with its target audience. | H18: To Be Confirmed | I18: Cardinality TBC (OD-20) | J18: Explicitly listed as Related Reference; exact cardinality is not stated. | [Merge Log] DC-17 (=MAP-007), DC-23
A19: TR-018 | B19: Marketing Campaign | C19: TBC | D19: Has / Incurs | E19: Campaign Cost | F19: Transactional (Team 2 catalog) | G19: A Marketing Campaign has associated campaign cost transactions. | H19: To Be Confirmed | I19: Inverse pair with TR-020; Cardinality TBC (OD-19, OD-20) | J19: Explicitly listed as Related Transaction. Campaign Cost also points back to Marketing Campaign. | [Merge Log] DC-15, DC-23
A20: TR-019 | B20: Marketing Campaign | C20: TBC | D20: Uses / Includes | E20: Promotion | F20: Transactional (Team 2 catalog) | G20: A Promotion is used/defined in the context of a Marketing Campaign. | H20: To Be Confirmed | I20: Inverse pair with TR-021; Cardinality TBC (OD-19, OD-20) | J20: Explicitly listed as Related Transaction. The source does not explicitly state whether every campaign must have a Promotion. | [Merge Log] DC-16, DC-23
A21: TR-020 | B21: Campaign Cost | C21: TBC | D21: Belongs To / Relates To | E21: Marketing Campaign | F21: Transactional (Team 2 catalog) | G21: Campaign Cost records are associated with the Marketing Campaign for which the cost is incurred. | H21: To Be Confirmed | I21: Inverse pair with TR-018; Cardinality TBC (OD-19, OD-20) | J21: Campaign_ID is explicitly stated as related to Marketing Campaign. | [Merge Log] DC-15, DC-23
A22: TR-021 | B22: Promotion | C22: TBC | D22: Used In / Defined For | E22: Marketing Campaign | F22: Transactional (Team 2 catalog) | G22: A Promotion is defined and used in the context of a Marketing Campaign. | H22: To Be Confirmed | I22: Inverse pair with TR-019; Cardinality TBC (OD-19, OD-20) | J22: Explicitly listed as Related Transaction; Promotion is a shared entity owned primarily by Team 1. | [Merge Log] DC-16, DC-23
A23: TR-022 | B23: Promotion | C23: TBC | D23: Applied To | E23: Sales Order | F23: Transactional (Team 1) | G23: A Promotion can be applied when a Sales Order is recorded. | H23: To Be Confirmed | I23: Cardinality TBC (OD-20) | J23: Explicitly listed as Related Transaction. The source explicitly leaves the application level (order header vs line item) unconfirmed. | [Merge Log] DC-23; OD-18

Sheet Shared Data
A1: Shared ID | B1: Entity | C1: Type | D1: Primary Owner | E1: Consumer / Related | F1: نقش Team 2 | G1: Status | H1: Linked
A2: SD-01 | B2: Promotion | C2: Transactional | D2: Team 1 | E2: Team 2 (Marketing Campaign) | F2: فقط خاستگاه/منطق بازاریابی؛ اعمال روی Sales Order با Team 1 | G2: Confirmed در منبع | H2: OD-09, OD-18
A3: SD-02 | B3: Sales Order | C3: Transactional (Team 1) | D3: Team 1 | E3: Promotion (TR-022) | F3: تعریف نمی‌شود؛ فقط ارجاع | G3: Confirmed در منبع | H3: OD-18
A4: SD-03 | B4: Product Category | C4: Reference | D4: Product & Marketing | E4: Sales/Contract/Invoice Item (Team 1)، از طریق Product | F4: مصرف غیرمستقیم؛ تراکنش مستقیم Team 2 ندارد | G4: نیازمند تأیید با Team 1 | H4: OD-21, OD-22
A5: SD-04 | B5: Product Subcategory | C5: Reference | D5: Product & Marketing | E5: مانند SD-03 | F5: مانند SD-03 | G5: نیازمند تأیید با Team 1 | H5: OD-21, OD-22
A6: SD-05 | B6: Package | C6: Reference | D6: Product & Marketing | E6: تراکنش‌های فروش Team 1 (از طریق SKU) | F6: مصرف غیرمستقیم | G6: نیازمند تأیید با Team 1 | H6: OD-22, OD-23
A7: SD-06 | B7: Unit Of Measure | C7: Reference | D7: Product & Marketing | E7: تراکنش‌های Team 1 (از طریق SKU/Product) | F7: مصرف غیرمستقیم | G7: نیازمند تأیید با Team 1 | H7: OD-22, OD-23
A8: SD-07 | B8: Product Price | C8: Reference | D8: Product & Marketing (تصمیم‌گیر: فروش/قیمت‌گذاری) | E8: Sales/Contract/Invoice Item، Order_Line_Item (Team 1) | F8: مصرف غیرمستقیم | G8: نیازمند تأیید با Team 1 | H8: OD-22, OD-24
A9: SD-08 | B9: Product (Master) | C9: Master | D9: TBC | E9: Market Price (TR-006)، Referenceهای محصول | F9: ارجاع از Market Price | G9: Candidate؛ مالک مشخص نیست | H9: OD-14
A10: SD-09 | B10: Brand (Master) | C10: Master | D10: TBC | E10: Brand Activity، Brand Campaign | F10: ارجاع | G10: Candidate؛ مالک مشخص نیست | H10: OD-14
A11: SD-10 | B11: Competitor (Master) | C11: Master | D11: TBC | E11: Market Price (TR-007) | F11: ارجاع | G11: Candidate؛ مالک مشخص نیست | H11: OD-14
A12: SD-11 | B12: Market / Market Segment | C12: نامشخص | D12: TBC | E12: Market Research / Survey | F12: ارجاع؛ در هیچ کاتالوگ نیست | G12: Candidate؛ طبقه‌بندی باز | H12: OD-04, OD-05
... A15: SD-14 | B15: Market Price | C15: Transactional | D15: Marketing / Sales | E15: Sales | F15: مالک مشترک؟ | G15: Candidate؛ تفکیک مالکیت باز | H15: OD-15

Sheet Duplicate & Conflict Log
A1: Log ID | B1: Type | C1: موضوع | D1: منبع A | E1: منبع B | F1: شرح | G1: Resolution | H1: Linked OD
A2: DC-01 | B2: Duplicate (دو نسخه) | C2: Market Research / Survey / Price | D2: فایل 06 | E2: 4-6market | F2: سه Entity در دو منبع با مقادیر متفاوت؛ نسخه مرجع مشخص نیست | G2: Open (هیچ‌چیز حذف نشده) | H2: OD-01
A3: DC-02 | B3: Definition Conflict | C3: Market Research: Related Transaction | D3: Market Survey | E3: Research Result | F3: Research Result در لیست ۸ Transaction نیست | G3: Open (هیچ‌چیز حذف نشده) | H3: OD-02
A4: DC-03 | B4: Definition Conflict | C4: Market Research: Master / Reference | D4: «—» / «—» | E4: Market / Market Research Type | F4: رابطه‌ها فقط در یک منبع آمده | G4: Open (هیچ‌چیز حذف نشده) | H4: OD-03, OD-04
A5: DC-04 | B5: Definition Conflict | C5: Market Survey: Reference | D5: Market Segment | E5: Survey Method (+ Market/Customer Segment به‌عنوان Master) | F5: دو منبع دو Reference متفاوت ثبت کرده‌اند | G5: Open (هیچ‌چیز حذف نشده) | H5: OD-03, OD-05
A6: DC-05 | B6: Classification Conflict | C6: Market | D6: Master (Research و Survey در 4-6market) | E6: Reference (Market Price در 4-6market) | F6: تناقض داخل یک فایل | G6: Open (هیچ‌چیز حذف نشده) | H6: OD-04
A7: DC-06 | B7: Definition Conflict | C7: Market Survey | D7: «فعالیت/ابزار Survey» (06) | E7: «اجرای Survey» (4-6market)؛ Notes: ابزار/روش | F7: فعالیت در برابر ابزار؛ Survey Method جداست | G7: Open (هیچ‌چیز حذف نشده) | H7: OD-01
A8: DC-07 | B8: Definition Conflict | C8: ستون Status | D8: نام Attribute (مثلاً Research_Status) | E8: مقدار «Active» | F8: دو معنای متفاوت؛ Market Price و Campaign Cost «—» در 06؛ Market Price «Active» در 4-6market | G8: Open (هیچ‌چیز حذف نشده) | H8: OD-27
A9: DC-08 | B9: Naming Conflict | C9: Transaction Type / Related Process | D9: Research Activity، Survey Activity، Price Observation؛ Market Research | E9: Market Research/Survey/Price Activity/Observation؛ Market Research Management | F9: پیشوند «Market» و «Management» فرق دارد | G9: Open (هیچ‌چیز حذف نشده) | H9: OD-01
A10: DC-09 | B10: Naming Conflict | C10: Business Date | D10: Start_Date / End_Date، Survey_Date، Price_Date | E10: Research Start Date / TBC، Survey Date، Price Date | F10: Underscore در برابر فاصله؛ تاریخ پایان Research در 4-6market TBC | G10: Open (هیچ‌چیز حذف نشده) | H10: OD-28
A11: DC-10 | B11: Overlap | C11: Campaign Cost | D11: Attribute در Brand Campaign | E11: Entity مستقل Campaign Cost (مرتبط فقط با Marketing Campaign) | F11: ریسک دوباره‌شماری | G11: Open (هیچ‌چیز حذف نشده) | H11: OD-07
A12: DC-11 | B12: Classification Conflict | C12: Campaign Cost: Reference یا Transaction | D12: TR-014: Related Reference | E12: کاتالوگ 06: Related Transaction | F12: یادداشت TR-014 با کاتالوگ نمی‌خواند | G12: Open (هیچ‌چیز حذف نشده) | H12: OD-07
... A36: DC-35 | B36: Definition Conflict | C36: Status در Reference Catalog | D36: Open / Defined = وضعیت تعریف/تأیید Entity | E36: Status در Transactional Catalog = نام Attribute (Business Lifecycle) | F36: دو مفهوم متفاوت از Status در دو Catalog | G36: Open (هیچ‌چیز حذف نشده) | H36: OD-27

Sheet Open Decisions
A1: OD ID | B1: موضوع | C1: تصمیم باز | D1: Affected | E1: تصمیم از | F1: منبع | G1: Status
A2: OD-01 | B2: نسخه مرجع Market | C2: کدام نسخه (06 یا 4-6market) مرجع است؟ | D2: Market Research/Survey/Price | E2: Task Owner / Marketing | F2: DC-01, DC-06, DC-08, OI-10 | G2: Open
A3: OD-02 | B3: Research Result | C3: آیا در Final Entity Catalog هست و چه رابطه‌ای با Market Research دارد؟ | D3: Market Research | E3: Data Governance | F3: DC-02 | G3: Open
A4: OD-03 | B4: Market Research Type و Survey Method | C4: آیا Reference تأییدشده‌اند؟ | D4: TR-003, TR-005 | E4: Marketing / Data Governance | F4: OI-01, OI-02, DC-03, DC-04 | G4: Open
A5: OD-04 | B5: Market | C5: Master یا Reference؟ در Final Catalog هست؟ | D5: TR-002, Market Price | E5: Marketing / Data Governance | F5: OI-03, DC-03, DC-05 | G5: Open
A6: OD-05 | B6: Market Segment / Customer Segment | C6: یک Entity یا دو؟ طبقه‌بندی؟ | D6: TR-004, Market Survey | E6: Marketing / Data Governance | F6: OI-02, DC-04 | G6: Open
A7: OD-06 | B7: Brand Campaign Type | C7: همان Campaign Type است؟ | D7: TR-011, MAP-002 | E7: Marketing | F7: DC-20 | G7: Open
A8: OD-07 | B8: Campaign Cost | C8: Transactional یا Reference؟ پوشش هزینه Brand Campaign؟ قاعده ضد دوباره‌شماری؟ | D8: Brand Campaign, Campaign Cost | E8: Marketing / Finance | F8: DC-10, DC-11 | G8: Open
A9: OD-08 | B9: Status برای Market Price و Campaign Cost | C9: در Stage 05 تعریف نشده؛ آیا لازم است؟ (حدس زده نشد) | D9: دو Entity | E9: Marketing | F9: DC-07 | G9: Open
A10: OD-09 | B10: طبقه‌بندی Promotion | C10: Grain «یک تعریف» است؛ آیا Transactional درست است؟ | D10: Promotion | E10: Team 1 | F10: SD-01 | G10: Open
A11: OD-10 | B11: تعارض طبقه‌بندی Planning/Reference | C11: Marketing Campaign و Market Research | D11: دو Entity | E11: Data Governance | F11: DC-14 | G11: Open
A12: OD-11 | B12: فهرست مقادیر Promotion_Type، Discount_Type، Promotion_Status (و Campaign_Status) | C12: Entity مرجع کدام است؟ | D12: Promotion, Marketing Campaign | E12: Team 1 | F12: OI-05 | G12: Open
... A33: OD-32 | B33: تطبیق با Final Entity Catalog | C33: هر ۱۶ Entity (۸ Transactional + ۸ Reference) باید در Final Entity Catalog وجود داشته باشد؛ شامل تأیید اینکه Market Research/Survey/Price در Scope Team 2 هستند | D33: همه شیت‌ها | E33: Task Owner | F33: Validation | G33: Open

Sheet Validation
A1: # | B1: Check | C1: Expected | D1: Result | E1: Status | F1: Notes
A2: 1 | B2: Transactional entities | C2: 8 | D2: =COUNTA('Transactional Catalog'!A2:A100) -> 8 | E2: =IF(D2=C2,"Pass","Fail") -> Pass | F2: Entity-های تأییدشده Team 2
A3: 2 | B3: Reference entities | C3: 8 | D3: =COUNTA('Reference Catalog'!A2:A100) -> 8 | E3: =IF(D3=C3,"Pass","Fail") -> Pass | F3: ۳ Campaign + ۵ Product
A4: 3 | B4: Transactions with Business Event & Grain | C4: 8 | D4: =SUMPRODUCT(('Transactional Catalog'!E2:E9<>"")*('Transactional Catalog'!F2:F9<>"")) -> 8 | E4: =IF(D4=C4,"Pass","Fail") -> Pass
A5: 4 | B5: References with Definition & Purpose | C5: 8 | D5: =SUMPRODUCT(('Reference Catalog'!B2:B9<>"")*('Reference Catalog'!C2:C9<>"")) -> 8 | E5: =IF(D5=C5,"Pass","Fail") -> Pass
A6: 5 | B6: Transactions with Status defined | C6: 8 | D6: =SUMPRODUCT(('Transactional Catalog'!H2:H9<>"—")*('Transactional Catalog'!H2:H9<>"")) -> 6 | E6: =IF(D6=C6,"Pass","Warn") -> Warn | F6: Market Price و Campaign Cost «—» → OD-08
A7: 6 | B7: Transactions with Owner defined | C7: 8 | D7: =SUMPRODUCT(('Transactional Catalog'!J2:J9<>"To Be Confirmed")*('Transactional Catalog'!J2:J9<>"")) -> 6 | E7: =IF(D7=C7,"Pass","Warn") -> Warn | F7: Brand Activity/Campaign: TBC؛ ۲ Owner دوگانه → OD-15
A8: 7 | B8: References with Status = Defined | C8: 8 | D8: =COUNTIF('Reference Catalog'!H2:H9,"Defined") -> 2 | E8: =IF(D8=C8,"Pass","Open") -> Open | F8: Package و UOM؛ بقیه Open
A9: 8 | B9: Mapping rows | C9: 7 | D9: =COUNTA('Reference-Transaction Mapping'!A2:A200) -> 7 | E9: =IF(D9=C9,"Pass","Fail") -> Pass
A10: 9 | B10: Duplicate Mapping IDs | C10: 0 | D10: =SUMPRODUCT(('Reference-Transaction Mapping'!A2:A8<>"")*(COUNTIF('Reference-Transaction Mapping'!A2:A8,'Reference-Transaction Mapping'!A2:A8)>1)) -> 0 | E10: =IF(D10=C10,"Pass","Fail") -> Pass
A11: 10 | B11: Mapping: transactions not in catalog | C11: 0 | D11: =SUMPRODUCT(('Reference-Transaction Mapping'!B2:B8<>"")*(COUNTIF('Transactional Catalog'!A2:A9,'Reference-Transaction Mapping'!B2:B8)=0)) -> 0 | E11: =IF(D11=C11,"Pass","Fail") -> Pass
A12: 11 | B12: Mapping: references not in catalog | C12: 0 | D12: =SUMPRODUCT(('Reference-Transaction Mapping'!C2:C8<>"")*(COUNTIF('Reference Catalog'!A2:A9,'Reference-Transaction Mapping'!C2:C8)=0)) -> 0 | E12: =IF(D12=C12,"Pass","Fail") -> Pass
A13: 12 | B13: Mapping: Mandatory? = To Be Confirmed | C13: 0 | D13: =COUNTIF('Reference-Transaction Mapping'!E2:E8,"To Be Confirmed") -> 7 | E13: =IF(D13=C13,"Pass","Open") -> Open | F13: → OD-16
A14: 13 | B14: Transactions without mapping | C14: - | D14: =SUMPRODUCT(--(COUNTIF('Reference-Transaction Mapping'!B2:B8,'Transactional Catalog'!A2:A9)=0)) -> 5 | E14: Info | F14: Market Research/Survey/Price، Campaign Cost، Promotion
A15: 14 | B15: References not used by Team 2 transactions | C15: - | D15: =SUMPRODUCT(--(COUNTIF('Reference-Transaction Mapping'!C2:C8,'Reference Catalog'!A2:A9)=0)) -> 5 | E15: Info | F15: ۵ Reference محصول → OD-22
A16: 15 | B16: Relationship rows | C16: 22 | D16: =COUNTA('Transaction Relationships'!A2:A100) -> 22 | E16: =IF(D16=C16,"Pass","Fail") -> Pass
A17: 16 | B17: Duplicate Relationship IDs | C17: 0 | D17: =SUMPRODUCT(('Transaction Relationships'!A2:A23<>"")*(COUNTIF('Transaction Relationships'!A2:A23,'Transaction Relationships'!A2:A23)>1)) -> 0 | E17: =IF(D17=C17,"Pass","Fail") -> Pass
A18: 17 | B18: Relationships: From Entity not in transactional catalog | C18: 0 | D18: =SUMPRODUCT(('Transaction Relationships'!B2:B23<>"")*(COUNTIF('Transactional Catalog'!A2:A9,'Transaction Relationships'!B2:B23)=0)) -> 0 | E18: =IF(D18=C18,"Pass","Fail") -> Pass
A19: 18 | B19: Relationship rows with unclassified To Entity (not catalog / not documented Master / not Team 1) | C19: 0 | D19: =COUNTIF('Transaction Relationships'!F2:F23,"Unclassified*") -> 5 | E19: =IF(D19=C19,"Pass","Open") -> Open | F19: Market, Market Research Type, Market Segment, Survey Method, Brand Campaign Type → OD-03..OD-06. Master (Product/Brand/Competitor) و Sales Order (Team 1) مجازند و Class دارند
A20: 19 | B20: Relationships: Mandatory? = To Be Confirmed | C20: - | D20: =COUNTIF('Transaction Relationships'!H2:H23,"To Be Confirmed") -> 16 | E20: Info | F20: Yes: 5، No: 1
A21: 20 | B21: Relationships with standard Relationship Type (1:1, 1:N, N:1, N:M, TBC) | C21: 22 | D21: =COUNTIF('Transaction Relationships'!C2:C23,"1:N")+COUNTIF('Transaction Relationships'!C2:C23,"N:1")+COUNTIF('Transaction Relationships'!C2:C23,"N:M")+COUNTIF('Transaction Relationships'!C2:C23,"1:1")+COUNTIF('Transaction Relationships'!C2:C23,"TBC") -> 22 | E21: =IF(D21=C21,"Pass","Fail") -> Pass | F21: Verb در ستون جداگانه
A22: 21 | B22: Relationships with Cardinality = TBC | C22: - | D22: =COUNTIF('Transaction Relationships'!C2:C23,"TBC") -> 10 | E22: Info | F22: TR-013..TR-022 → OD-20
A23: 22 | B23: Relationships flagged in Cardinality Review | C23: - | D23: =COUNTA('Transaction Relationships'!I2:I23) -> 14 | E23: Info | F23: TR-002, 004, 011, 012 + ردیف‌های TBC
A24: 23 | B24: Shared Data rows | C24: - | D24: =COUNTA('Shared Data'!A2:A100) -> 14 | E24: Info | F24: Confirmed: 2؛ بقیه Candidate/نیازمند تأیید
A25: 24 | B25: Duplicate & Conflict Log rows | C25: - | D25: =COUNTA('Duplicate & Conflict Log'!A2:A200) -> 35 | E25: Info | F25: هیچ موردی حذف نشده
A26: 25 | B26: Open Decisions rows | C26: - | D26: =COUNTA('Open Decisions'!A2:A200) -> 32 | E26: Info
A27: 26 | B27: Final Entity Catalog cross-check (16 entities) | C27: 16 | D27: Not performed | E27: Open | F27: → OD-32؛ سند دریافت نشد
A28: 27 | B28: New entities created outside Final Entity Catalog | C28: 0 | D28: 0 | E28: Pass | F28: Process check: هیچ Entity جدیدی ساخته نشد
A29: 28 | B29: Shared / Duplicate / Conflict items deleted | C29: 0 | D29: 0 | E29: Pass | F29: Process check: هیچ مورد حذف نشد
A30: 29 | B30: Naming Standard compliance | C30: - | D30: - | E30: Not verifiable | F30: سند Naming Standard دریافت نشد؛ فقط سازگاری داخلی بررسی شد (DC-08, DC-25, DC-26, DC-30..DC-32)
A31: 30 | B31: Definition of Done (Task 4.6 guideline) | C31: - | D31: Pending reviewer check | E31: Open | F31: تطبیق نهایی با راهنمای Task 4.6 باید توسط Reviewer انجام شود؛ در این Merge فقط Acceptance Criteria متن تسک بررسی شده است
B33: Overall status | E33: =IF(COUNTIF(E2:E31,"Fail")+COUNTIF(E2:E31,"Open")>0,"Draft - not ready for final sign-off","Ready for review") -> Draft - not ready for final sign-off | F33: Fail ها در ردیف‌های بالا مشخص‌اند؛ Open/Warn به Open Decisions ارجاع دارند
B34: Final Entity Catalog | E34: Not received | F34: لیست ۸+۸ از Validation فایل Mapping به‌عنوان جایگزین استفاده شد
